petpy/__init__.py
petpy/api.py
petpy/exceptions.py
petpy/petpy_types.py
petpy-2.4.22.dist-info/LICENSE.txt
petpy-2.4.22.dist-info/METADATA
petpy-2.4.22.dist-info/WHEEL
petpy-2.4.22.dist-info/top_level.txt
petpy-2.4.22.dist-info/RECORD
